kivymd/__init__.py
kivymd/_version.py
kivymd/app.py
kivymd/color_definitions.py
kivymd/factory_registers.py
kivymd/font_definitions.py
kivymd/icon_definitions.py
kivymd/material_resources.py
kivymd/theming.py
kivymd/theming_dynamic_text.py
kivymd/effects/__init__.py
kivymd/effects/fadingedge/__init__.py
kivymd/effects/fadingedge/fadingedge.py
kivymd/effects/roulettescroll/__init__.py
kivymd/effects/roulettescroll/roulettescroll.py
kivymd/effects/stiffscroll/__init__.py
kivymd/effects/stiffscroll/stiffscroll.py
kivymd/fonts/Roboto-Black.ttf
kivymd/fonts/Roboto-BlackItalic.ttf
kivymd/fonts/Roboto-Bold.ttf
kivymd/fonts/Roboto-BoldItalic.ttf
kivymd/fonts/Roboto-Italic.ttf
kivymd/fonts/Roboto-Light.ttf
kivymd/fonts/Roboto-LightItalic.ttf
kivymd/fonts/Roboto-Medium.ttf
kivymd/fonts/Roboto-MediumItalic.ttf
kivymd/fonts/Roboto-Regular.ttf
kivymd/fonts/Roboto-Thin.ttf
kivymd/fonts/Roboto-ThinItalic.ttf
kivymd/fonts/materialdesignicons-webfont.ttf
kivymd/images/alpha_layer.png
kivymd/images/black.png
kivymd/images/blue.png
kivymd/images/folder.png
kivymd/images/green.png
kivymd/images/quad_shadow-0.png
kivymd/images/quad_shadow-1.png
kivymd/images/quad_shadow-2.png
kivymd/images/quad_shadow.atlas
kivymd/images/rec_shadow-0.png
kivymd/images/rec_shadow-1.png
kivymd/images/rec_shadow.atlas
kivymd/images/rec_st_shadow-0.png
kivymd/images/rec_st_shadow-1.png
kivymd/images/rec_st_shadow-2.png
kivymd/images/rec_st_shadow.atlas
kivymd/images/red.png
kivymd/images/round_shadow-0.png
kivymd/images/round_shadow-1.png
kivymd/images/round_shadow-2.png
kivymd/images/round_shadow.atlas
kivymd/images/transparent.png
kivymd/images/yellow.png
kivymd/toast/__init__.py
kivymd/toast/androidtoast/__init__.py
kivymd/toast/androidtoast/androidtoast.py
kivymd/toast/kivytoast/__init__.py
kivymd/toast/kivytoast/kivytoast.py
kivymd/tools/__init__.py
kivymd/tools/argument_parser.py
kivymd/tools/hotreload/__init__.py
kivymd/tools/hotreload/app.py
kivymd/tools/packaging/__init__.py
kivymd-1.0.2.dist-info/LICENSE
kivymd-1.0.2.dist-info/METADATA
kivymd-1.0.2.dist-info/WHEEL
kivymd-1.0.2.dist-info/entry_points.txt
kivymd-1.0.2.dist-info/top_level.txt
kivymd-1.0.2.dist-info/RECORD
