Metadata-Version: 2.1
Name: kivymd
Version: 1.0.2
Summary: Set of widgets for Kivy inspired by Google's Material Design
Home-page: https://github.com/kivymd/KivyMD
Author: Andres Rodriguez, fork author - HeaTTheatR
Author-email: kivydevelopment@gmail.com
License: MIT
Project-URL: Documentation, https://kivymd.readthedocs.io
Project-URL: Wiki, https://github.com/kivymd/KivyMD/wiki
Project-URL: Tracker, https://github.com/kivymd/KivyMD/issues
Keywords: kivymd,kivy,material,ui
Platform: any
Classifier: Development Status :: 4 - Beta
Classifier: License :: OSI Approved :: MIT License
Classifier: Programming Language :: Python :: 3 :: Only
Classifier: Programming Language :: Python :: 3
Classifier: Programming Language :: Python :: 3.6
Classifier: Programming Language :: Python :: 3.7
Classifier: Programming Language :: Python :: 3.8
Classifier: Programming Language :: Python :: 3.9
Classifier: Programming Language :: Python :: 3.10
Classifier: Programming Language :: Python :: 3.11
Classifier: Operating System :: OS Independent
Classifier: Operating System :: Android
Classifier: Operating System :: POSIX :: Linux
Classifier: Operating System :: POSIX :: BSD :: FreeBSD
Classifier: Operating System :: Microsoft :: Windows
Classifier: Operating System :: iOS
Classifier: Operating System :: MacOS
Classifier: Operating System :: MacOS :: MacOS X
Classifier: Environment :: MacOS X
Classifier: Environment :: Win32 (MS Windows)
Classifier: Environment :: X11 Applications
Classifier: Intended Audience :: Developers
Classifier: Intended Audience :: End Users/Desktop
Classifier: Intended Audience :: Information Technology
Classifier: Intended Audience :: Science/Research
Classifier: Topic :: Software Development :: User Interfaces
Classifier: Topic :: Scientific/Engineering :: Human Machine Interfaces
Classifier: Topic :: Scientific/Engineering :: Visualization
Requires-Python: >=3.6
Provides-Extra: dev
Provides-Extra: docs
License-File: LICENSE
